CHANGES.rst
CONTRIBUTORS.rst
DEVELOP.rst
LICENSE.GPL
LICENSE.rst
MANIFEST.in
README.rst
setup.cfg
setup.py
docs/conf.py
docs/index.rst
docs/screenshot-ignored-users.png
docs/screenshot.png
src/collective/__init__.py
src/collective.localrolesoverview.egg-info/PKG-INFO
src/collective.localrolesoverview.egg-info/SOURCES.txt
src/collective.localrolesoverview.egg-info/dependency_links.txt
src/collective.localrolesoverview.egg-info/entry_points.txt
src/collective.localrolesoverview.egg-info/namespace_packages.txt
src/collective.localrolesoverview.egg-info/not-zip-safe
src/collective.localrolesoverview.egg-info/requires.txt
src/collective.localrolesoverview.egg-info/top_level.txt
src/collective/localrolesoverview/__init__.py
src/collective/localrolesoverview/configure.zcml
src/collective/localrolesoverview/interfaces.py
src/collective/localrolesoverview/permissions.zcml
src/collective/localrolesoverview/setuphandlers.py
src/collective/localrolesoverview/testing.py
src/collective/localrolesoverview/utils.py
src/collective/localrolesoverview/browser/__init__.py
src/collective/localrolesoverview/browser/configure.zcml
src/collective/localrolesoverview/browser/overrides/.gitkeep
src/collective/localrolesoverview/browser/static/.gitkeep
src/collective/localrolesoverview/browser/static/main.css
src/collective/localrolesoverview/locales/README.rst
src/collective/localrolesoverview/locales/__init__.py
src/collective/localrolesoverview/locales/collective.permissionsoverview.pot
src/collective/localrolesoverview/locales/update.py
src/collective/localrolesoverview/locales/update.sh
src/collective/localrolesoverview/locales/en/LC_MESSAGES/collective.permissionsoverview.po
src/collective/localrolesoverview/profiles/default/browserlayer.xml
src/collective/localrolesoverview/profiles/default/catalog.xml
src/collective/localrolesoverview/profiles/default/metadata.xml
src/collective/localrolesoverview/profiles/default/rolemap.xml
src/collective/localrolesoverview/profiles/default/registry/main.xml
src/collective/localrolesoverview/profiles/uninstall/browserlayer.xml
src/collective/localrolesoverview/tests/__init__.py
src/collective/localrolesoverview/tests/test_robot.py
src/collective/localrolesoverview/tests/test_setup.py
src/collective/localrolesoverview/tests/test_view_permissions_overview.py
src/collective/localrolesoverview/tests/robot/test_example.robot
src/collective/localrolesoverview/views/__init__.py
